leap.soledad-0.10.7-py2.7-nspkg.pth
leap/soledad/__init__.py
leap/soledad/_version.py
leap/soledad/client/__init__.py
leap/soledad/client/_crypto.py
leap/soledad/client/_document.py
leap/soledad/client/_http.py
leap/soledad/client/_pipes.py
leap/soledad/client/_recovery_code.py
leap/soledad/client/_scrypt.py
leap/soledad/client/api.py
leap/soledad/client/auth.py
leap/soledad/client/crypto.py
leap/soledad/client/events.py
leap/soledad/client/incoming.py
leap/soledad/client/interfaces.py
leap/soledad/client/shared_db.py
leap/soledad/client/sync.py
leap/soledad/client/_db/__init__.py
leap/soledad/client/_db/adbapi.py
leap/soledad/client/_db/dbschema.sql
leap/soledad/client/_db/pragmas.py
leap/soledad/client/_db/sqlcipher.py
leap/soledad/client/_db/sqlite.py
leap/soledad/client/_db/blobs/__init__.py
leap/soledad/client/_db/blobs/__main__.py
leap/soledad/client/_db/blobs/errors.py
leap/soledad/client/_db/blobs/sql.py
leap/soledad/client/_db/blobs/sync.py
leap/soledad/client/_db/blobs/upstream_producer.py
leap/soledad/client/_secrets/__init__.py
leap/soledad/client/_secrets/crypto.py
leap/soledad/client/_secrets/storage.py
leap/soledad/client/_secrets/util.py
leap/soledad/client/http_target/__init__.py
leap/soledad/client/http_target/api.py
leap/soledad/client/http_target/fetch.py
leap/soledad/client/http_target/fetch_protocol.py
leap/soledad/client/http_target/send.py
leap/soledad/client/http_target/send_protocol.py
leap/soledad/client/http_target/support.py
leap/soledad/common/__init__.py
leap/soledad/common/backend.py
leap/soledad/common/command.py
leap/soledad/common/crypto.py
leap/soledad/common/document.py
leap/soledad/common/errors.py
leap/soledad/common/log.py
leap/soledad/common/blobs/__init__.py
leap/soledad/common/blobs/preamble.py
leap/soledad/common/couch/__init__.py
leap/soledad/common/couch/check.py
leap/soledad/common/couch/state.py
leap/soledad/common/couch/support.py
leap.soledad-0.10.7.dist-info/DESCRIPTION.rst
leap.soledad-0.10.7.dist-info/METADATA
leap.soledad-0.10.7.dist-info/RECORD
leap.soledad-0.10.7.dist-info/WHEEL
leap.soledad-0.10.7.dist-info/entry_points.txt
leap.soledad-0.10.7.dist-info/metadata.json
leap.soledad-0.10.7.dist-info/namespace_packages.txt
leap.soledad-0.10.7.dist-info/top_level.txt
