Metadata-Version: 2.0
Name: leap.soledad
Version: 0.10.7
Summary: Synchronization of locally encrypted data among devices.
Home-page: https://soledad.readthedocs.io/
Author: LEAP Encryption Access Project
Author-email: info@leap.se
License: GPLv3+
Download-URL: https://github.com/leapcode/soledad/archive/0.10.7.tar.gz
Platform: UNKNOWN
Classifier: Intended Audience :: Developers
Classifier: License :: OSI Approved :: GNU General Public License v3 or later (GPLv3+)
Classifier: Environment :: Console
Classifier: Operating System :: OS Independent
Classifier: Operating System :: POSIX
Classifier: Programming Language :: Python :: 2.7
Classifier: Topic :: Database :: Front-Ends
Classifier: Topic :: Software Development :: Libraries :: Python Modules
Requires-Dist: leap.common
Requires-Dist: paste
Requires-Dist: pyasn1
Requires-Dist: routes
Requires-Dist: service-identity
Requires-Dist: six
Requires-Dist: treq
Requires-Dist: twisted
Provides-Extra: client
Requires-Dist: cryptography; extra == 'client'
Requires-Dist: pysqlcipher; extra == 'client'
Requires-Dist: scrypt; extra == 'client'
Requires-Dist: zope.proxy; extra == 'client'
Provides-Extra: server
Requires-Dist: Beaker; extra == 'server'
Requires-Dist: configparser; extra == 'server'
Requires-Dist: couchdb; extra == 'server'
Provides-Extra: signaling
Requires-Dist: leap.common; extra == 'signaling'
